setup.py
common_pims.egg-info/PKG-INFO
common_pims.egg-info/SOURCES.txt
common_pims.egg-info/dependency_links.txt
common_pims.egg-info/requires.txt
common_pims.egg-info/top_level.txt
common_pims/lib/Context.py
common_pims/lib/ReplaceVariable.py
common_pims/lib/__init__.py
common_pims/lib/api.py
common_pims/lib/cookie_ui.py
common_pims/lib/newReport.py
common_pims/lib/parsley.py
common_pims/lib/public.py
common_pims/lib/readexcel.py
common_pims/lib/sendmail.py
common_pims/lib/utility.py
common_pims/lib/writeexcel.py
common_pims/package/HTMLTestRunner.py
common_pims/package/__init__.py