Metadata-Version: 1.0
Name: common-pims
Version: 1.0.0
Summary: common_pims
Home-page: UNKNOWN
Author: cxx
Author-email: cuixiaoxia@chinasofti.com
License: UNKNOWN
Platform: UNKNOWN
